{
    "id": "crm",
    "name": "Kundenhistorie",
    "description": "Verwalten von Interaktionen, Kontakten, Organisationen und Veranstaltungen innerhalb von Spaces.",
    "keywords": ["crm", "customer", "contacts", "interaction", "event"],
    "version": "1.0.0",
    "humhub": {
        "minVersion": "1.15.0"
    },
    "namespace": "humhub\\modules\\crm",
    "authors": [
        {
            "name": "Atilla Turan"
        }
    ],
    "resources": {
        "icons": "assets/icon.png"
    }
}
